odoo/addons/stock_orderpoint_procure_location/README.rst
odoo/addons/stock_orderpoint_procure_location/__init__.py
odoo/addons/stock_orderpoint_procure_location/__manifest__.py
odoo/addons/stock_orderpoint_procure_location/i18n/stock_orderpoint_procure_location.pot
odoo/addons/stock_orderpoint_procure_location/models/__init__.py
odoo/addons/stock_orderpoint_procure_location/models/procurement_group.py
odoo/addons/stock_orderpoint_procure_location/models/stock_warehouse_orderpoint.py
odoo/addons/stock_orderpoint_procure_location/static/description/icon.png
odoo/addons/stock_orderpoint_procure_location/tests/__init__.py
odoo/addons/stock_orderpoint_procure_location/tests/test_stock_orderpoint_procure_location.py
odoo/addons/stock_orderpoint_procure_location/views/stock_warehouse_orderpoint_view.xml
odoo11_addon_stock_orderpoint_procure_location-11.0.1.0.0.99.dev1.dist-info/METADATA
odoo11_addon_stock_orderpoint_procure_location-11.0.1.0.0.99.dev1.dist-info/WHEEL
odoo11_addon_stock_orderpoint_procure_location-11.0.1.0.0.99.dev1.dist-info/top_level.txt
odoo11_addon_stock_orderpoint_procure_location-11.0.1.0.0.99.dev1.dist-info/RECORD
